sqltables/__init__.py
sqltables/generic.py
sqltables/postgresql.py
sqltables/sqlite.py
sqltables/sqlite3.py
sqltables/sqltables.py
sqltables-1.8.dist-info/LICENSE
sqltables-1.8.dist-info/METADATA
sqltables-1.8.dist-info/WHEEL
sqltables-1.8.dist-info/top_level.txt
sqltables-1.8.dist-info/RECORD
