Metadata-Version: 2.1
Name: sqltables
Version: 1.8
Summary: SQL tables as first-class objects
Home-page: https://github.com/bobpepin/sqltables
Author: Bob Pepin
Author-email: pypi@pepin.io
Project-URL: Source, https://github.com/bobpepin/sqltables
Project-URL: Documentation, https://sqltables.readthedocs.io
Classifier: Programming Language :: Python :: 3
Classifier: License :: OSI Approved :: MIT License
Classifier: Operating System :: OS Independent
Requires-Python: >=3.6
License-File: LICENSE
